maximcrc/__init__.py
maximcrc/maximcrc.py
maximcrc-0.11.dist-info/LICENSE
maximcrc-0.11.dist-info/METADATA
maximcrc-0.11.dist-info/WHEEL
maximcrc-0.11.dist-info/top_level.txt
maximcrc-0.11.dist-info/RECORD
