Metadata-Version: 2.1
Name: maximcrc
Version: 0.11
Summary: Maxim CRC
Home-page: https://github.com/javatechy/dokr
Author: Fabio Dalla Libera
Author-email: fabiodl@gmail.com
License: UNKNOWN
Platform: UNKNOWN
Classifier: Programming Language :: Python :: 3
Classifier: License :: OSI Approved :: GNU General Public License (GPL)
Classifier: Operating System :: OS Independent
